{"name":"renderer","content":{"./node_modules/core-js/library/modules/_add-to-unscopables.js":{"id":"./node_modules/core-js/library/modules/_add-to-unscopables.js","buildMeta":{"providedExports":true}},"./node_modules/jquery/dist/jquery.js":{"id":"./node_modules/jquery/dist/jquery.js","buildMeta":{"providedExports":true}},"./node_modules/popper.js/dist/esm/popper.js":{"id":"./node_modules/popper.js/dist/esm/popper.js","buildMeta":{"exportsType":"namespace","providedExports":["default"]}},"./node_modules/devtron/api.js":{"id":"./node_modules/devtron/api.js","buildMeta":{"providedExports":true}},"electron":{"id":"electron","buildMeta":{"providedExports":true}},"./node_modules/electron-debug/index.js":{"id":"./node_modules/electron-debug/index.js","buildMeta":{"providedExports":true}},"./node_modules/electron-localshortcut/index.js":{"id":"./node_modules/electron-localshortcut/index.js","buildMeta":{"providedExports":true}},"./node_modules/electron-is-accelerator/index.js":{"id":"./node_modules/electron-is-accelerator/index.js","buildMeta":{"providedExports":true}},"./node_modules/keyboardevents-areequal/index.js":{"id":"./node_modules/keyboardevents-areequal/index.js","buildMeta":{"providedExports":true}},"./node_modules/keyboardevent-from-electron-accelerator/index.js":{"id":"./node_modules/keyboardevent-from-electron-accelerator/index.js","buildMeta":{"providedExports":true}},"./node_modules/debug/src/browser.js":{"id":"./node_modules/debug/src/browser.js","buildMeta":{"providedExports":true}},"./node_modules/debug/src/debug.js":{"id":"./node_modules/debug/src/debug.js","buildMeta":{"providedExports":true}},"./node_modules/ms/index.js":{"id":"./node_modules/ms/index.js","buildMeta":{"providedExports":true}},"./node_modules/electron-is-dev/index.js":{"id":"./node_modules/electron-is-dev/index.js","buildMeta":{"providedExports":true}},"./node_modules/electron-debug sync recursive":{"id":"./node_modules/electron-debug sync recursive","buildMeta":{"providedExports":true}},"./node_modules/history/es/index.js":{"id":"./node_modules/history/es/index.js","buildMeta":{"exportsType":"namespace","providedExports":["createBrowserHistory","createHashHistory","createMemoryHistory","createLocation","locationsAreEqual","parsePath","createPath"]}},"./node_modules/history/es/createBrowserHistory.js":{"id":"./node_modules/history/es/createBrowserHistory.js","buildMeta":{"exportsType":"namespace","providedExports":["default"]}},"./node_modules/warning/browser.js":{"id":"./node_modules/warning/browser.js","buildMeta":{"providedExports":true}},"./node_modules/invariant/browser.js":{"id":"./node_modules/invariant/browser.js","buildMeta":{"providedExports":true}},"./node_modules/history/es/LocationUtils.js":{"id":"./node_modules/history/es/LocationUtils.js","buildMeta":{"exportsType":"namespace","providedExports":["createLocation","locationsAreEqual"]}},"./node_modules/resolve-pathname/index.js":{"id":"./node_modules/resolve-pathname/index.js","buildMeta":{"exportsType":"namespace","providedExports":["default"]}},"./node_modules/value-equal/index.js":{"id":"./node_modules/value-equal/index.js","buildMeta":{"exportsType":"namespace","providedExports":["default"]}},"./node_modules/history/es/PathUtils.js":{"id":"./node_modules/history/es/PathUtils.js","buildMeta":{"exportsType":"namespace","providedExports":["addLeadingSlash","stripLeadingSlash","hasBasename","stripBasename","stripTrailingSlash","parsePath","createPath"]}},"./node_modules/history/es/createTransitionManager.js":{"id":"./node_modules/history/es/createTransitionManager.js","buildMeta":{"exportsType":"namespace","providedExports":["default"]}},"./node_modules/history/es/DOMUtils.js":{"id":"./node_modules/history/es/DOMUtils.js","buildMeta":{"exportsType":"namespace","providedExports":["canUseDOM","addEventListener","removeEventListener","getConfirmation","supportsHistory","supportsPopStateOnHashChange","supportsGoWithoutReloadUsingHash","isExtraneousPopstateEvent"]}},"./node_modules/history/es/createHashHistory.js":{"id":"./node_modules/history/es/createHashHistory.js","buildMeta":{"exportsType":"namespace","providedExports":["default"]}},"./node_modules/history/es/createMemoryHistory.js":{"id":"./node_modules/history/es/createMemoryHistory.js","buildMeta":{"exportsType":"namespace","providedExports":["default"]}},"./node_modules/mobx/lib/mobx.module.js":{"id":"./node_modules/mobx/lib/mobx.module.js","buildMeta":{"exportsType":"namespace","providedExports":["Reaction","untracked","IDerivationState","createAtom","spy","comparer","isObservableObject","isBoxedObservable","isObservableArray","ObservableMap","isObservableMap","transaction","observable","computed","isObservable","isObservableProp","isComputed","isComputedProp","extendObservable","observe","intercept","autorun","reaction","when","action","isAction","runInAction","keys","values","entries","set","remove","has","get","decorate","configure","onBecomeObserved","onBecomeUnobserved","flow","toJS","trace","getDependencyTree","getObserverTree","_resetGlobalState","_getGlobalState","getDebugName","getAtom","_getAdministration","_allowStateChanges","isArrayLike","$mobx","_isComputingDerivation","onReactionError","_interceptReads"]}},"./node_modules/mobx-state-tree/dist/mobx-state-tree.module.js":{"id":"./node_modules/mobx-state-tree/dist/mobx-state-tree.module.js","buildMeta":{"exportsType":"namespace","providedExports":["types","typecheck","escapeJsonPath","unescapeJsonPath","joinJsonPath","splitJsonPath","decorate","addMiddleware","process","isStateTreeNode","flow","applyAction","onAction","recordActions","createActionTrackingMiddleware","setLivelynessChecking","TypeFlags","getType","getChildType","onPatch","onSnapshot","applyPatch","recordPatches","protect","unprotect","isProtected","applySnapshot","getSnapshot","hasParent","getParent","hasParentOfType","getParentOfType","getRoot","getPath","getPathParts","isRoot","resolvePath","resolveIdentifier","getIdentifier","tryResolve","getRelativePath","clone","detach","destroy","isAlive","addDisposer","getEnv","walk","getMembers"]}},"./node_modules/react/index.js":{"id":"./node_modules/react/index.js","buildMeta":{"providedExports":true}},"./node_modules/react/cjs/react.development.js":{"id":"./node_modules/react/cjs/react.development.js","buildMeta":{"providedExports":true}},"./node_modules/object-assign/index.js":{"id":"./node_modules/object-assign/index.js","buildMeta":{"providedExports":true}},"./node_modules/fbjs/lib/invariant.js":{"id":"./node_modules/fbjs/lib/invariant.js","buildMeta":{"providedExports":true}},"./node_modules/fbjs/lib/emptyObject.js":{"id":"./node_modules/fbjs/lib/emptyObject.js","buildMeta":{"providedExports":true}},"./node_modules/fbjs/lib/warning.js":{"id":"./node_modules/fbjs/lib/warning.js","buildMeta":{"providedExports":true}},"./node_modules/fbjs/lib/emptyFunction.js":{"id":"./node_modules/fbjs/lib/emptyFunction.js","buildMeta":{"providedExports":true}},"./node_modules/prop-types/checkPropTypes.js":{"id":"./node_modules/prop-types/checkPropTypes.js","buildMeta":{"providedExports":true}},"./node_modules/prop-types/lib/ReactPropTypesSecret.js":{"id":"./node_modules/prop-types/lib/ReactPropTypesSecret.js","buildMeta":{"providedExports":true}},"./node_modules/react-dom/index.js":{"id":"./node_modules/react-dom/index.js","buildMeta":{"providedExports":true}},"./node_modules/react-dom/cjs/react-dom.development.js":{"id":"./node_modules/react-dom/cjs/react-dom.development.js","buildMeta":{"providedExports":true}},"./node_modules/fbjs/lib/ExecutionEnvironment.js":{"id":"./node_modules/fbjs/lib/ExecutionEnvironment.js","buildMeta":{"providedExports":true}},"./node_modules/fbjs/lib/getActiveElement.js":{"id":"./node_modules/fbjs/lib/getActiveElement.js","buildMeta":{"providedExports":true}},"./node_modules/fbjs/lib/shallowEqual.js":{"id":"./node_modules/fbjs/lib/shallowEqual.js","buildMeta":{"providedExports":true}},"./node_modules/fbjs/lib/containsNode.js":{"id":"./node_modules/fbjs/lib/containsNode.js","buildMeta":{"providedExports":true}},"./node_modules/fbjs/lib/isTextNode.js":{"id":"./node_modules/fbjs/lib/isTextNode.js","buildMeta":{"providedExports":true}},"./node_modules/fbjs/lib/isNode.js":{"id":"./node_modules/fbjs/lib/isNode.js","buildMeta":{"providedExports":true}},"./node_modules/fbjs/lib/hyphenateStyleName.js":{"id":"./node_modules/fbjs/lib/hyphenateStyleName.js","buildMeta":{"providedExports":true}},"./node_modules/fbjs/lib/hyphenate.js":{"id":"./node_modules/fbjs/lib/hyphenate.js","buildMeta":{"providedExports":true}},"./node_modules/fbjs/lib/camelizeStyleName.js":{"id":"./node_modules/fbjs/lib/camelizeStyleName.js","buildMeta":{"providedExports":true}},"./node_modules/fbjs/lib/camelize.js":{"id":"./node_modules/fbjs/lib/camelize.js","buildMeta":{"providedExports":true}},"./node_modules/react-hot-loader/index.js":{"id":"./node_modules/react-hot-loader/index.js","buildMeta":{"providedExports":true}},"./node_modules/react-hot-loader/dist/react-hot-loader.production.min.js":{"id":"./node_modules/react-hot-loader/dist/react-hot-loader.production.min.js","buildMeta":{"providedExports":true}},"./node_modules/react-popper/lib/esm/index.js":{"id":"./node_modules/react-popper/lib/esm/index.js","buildMeta":{"exportsType":"namespace","providedExports":["Popper","placements","Manager","Reference"]}},"./node_modules/react-popper/lib/esm/Popper.js":{"id":"./node_modules/react-popper/lib/esm/Popper.js","buildMeta":{"exportsType":"namespace","providedExports":["InnerPopper","placements","default"]}},"./node_modules/babel-runtime/helpers/extends.js":{"id":"./node_modules/babel-runtime/helpers/extends.js","buildMeta":{"providedExports":true}},"./node_modules/babel-runtime/core-js/object/assign.js":{"id":"./node_modules/babel-runtime/core-js/object/assign.js","buildMeta":{"providedExports":true}},"./node_modules/core-js/library/fn/object/assign.js":{"id":"./node_modules/core-js/library/fn/object/assign.js","buildMeta":{"providedExports":true}},"./node_modules/core-js/library/modules/es6.object.assign.js":{"id":"./node_modules/core-js/library/modules/es6.object.assign.js","buildMeta":{"providedExports":true}},"./node_modules/core-js/library/modules/_export.js":{"id":"./node_modules/core-js/library/modules/_export.js","buildMeta":{"providedExports":true}},"./node_modules/core-js/library/modules/_global.js":{"id":"./node_modules/core-js/library/modules/_global.js","buildMeta":{"providedExports":true}},"./node_modules/core-js/library/modules/_core.js":{"id":"./node_modules/core-js/library/modules/_core.js","buildMeta":{"providedExports":true}},"./node_modules/core-js/library/modules/_ctx.js":{"id":"./node_modules/core-js/library/modules/_ctx.js","buildMeta":{"providedExports":true}},"./node_modules/core-js/library/modules/_a-function.js":{"id":"./node_modules/core-js/library/modules/_a-function.js","buildMeta":{"providedExports":true}},"./node_modules/core-js/library/modules/_hide.js":{"id":"./node_modules/core-js/library/modules/_hide.js","buildMeta":{"providedExports":true}},"./node_modules/core-js/library/modules/_object-dp.js":{"id":"./node_modules/core-js/library/modules/_object-dp.js","buildMeta":{"providedExports":true}},"./node_modules/core-js/library/modules/_an-object.js":{"id":"./node_modules/core-js/library/modules/_an-object.js","buildMeta":{"providedExports":true}},"./node_modules/core-js/library/modules/_is-object.js":{"id":"./node_modules/core-js/library/modules/_is-object.js","buildMeta":{"providedExports":true}},"./node_modules/core-js/library/modules/_ie8-dom-define.js":{"id":"./node_modules/core-js/library/modules/_ie8-dom-define.js","buildMeta":{"providedExports":true}},"./node_modules/core-js/library/modules/_descriptors.js":{"id":"./node_modules/core-js/library/modules/_descriptors.js","buildMeta":{"providedExports":true}},"./node_modules/core-js/library/modules/_fails.js":{"id":"./node_modules/core-js/library/modules/_fails.js","buildMeta":{"providedExports":true}},"./node_modules/core-js/library/modules/_dom-create.js":{"id":"./node_modules/core-js/library/modules/_dom-create.js","buildMeta":{"providedExports":true}},"./node_modules/core-js/library/modules/_to-primitive.js":{"id":"./node_modules/core-js/library/modules/_to-primitive.js","buildMeta":{"providedExports":true}},"./node_modules/core-js/library/modules/_property-desc.js":{"id":"./node_modules/core-js/library/modules/_property-desc.js","buildMeta":{"providedExports":true}},"./node_modules/core-js/library/modules/_has.js":{"id":"./node_modules/core-js/library/modules/_has.js","buildMeta":{"providedExports":true}},"./node_modules/core-js/library/modules/_object-assign.js":{"id":"./node_modules/core-js/library/modules/_object-assign.js","buildMeta":{"providedExports":true}},"./node_modules/core-js/library/modules/_object-keys.js":{"id":"./node_modules/core-js/library/modules/_object-keys.js","buildMeta":{"providedExports":true}},"./node_modules/core-js/library/modules/_object-keys-internal.js":{"id":"./node_modules/core-js/library/modules/_object-keys-internal.js","buildMeta":{"providedExports":true}},"./node_modules/core-js/library/modules/_to-iobject.js":{"id":"./node_modules/core-js/library/modules/_to-iobject.js","buildMeta":{"providedExports":true}},"./node_modules/core-js/library/modules/_iobject.js":{"id":"./node_modules/core-js/library/modules/_iobject.js","buildMeta":{"providedExports":true}},"./node_modules/core-js/library/modules/_cof.js":{"id":"./node_modules/core-js/library/modules/_cof.js","buildMeta":{"providedExports":true}},"./node_modules/core-js/library/modules/_defined.js":{"id":"./node_modules/core-js/library/modules/_defined.js","buildMeta":{"providedExports":true}},"./node_modules/core-js/library/modules/_array-includes.js":{"id":"./node_modules/core-js/library/modules/_array-includes.js","buildMeta":{"providedExports":true}},"./node_modules/core-js/library/modules/_to-length.js":{"id":"./node_modules/core-js/library/modules/_to-length.js","buildMeta":{"providedExports":true}},"./node_modules/core-js/library/modules/_to-integer.js":{"id":"./node_modules/core-js/library/modules/_to-integer.js","buildMeta":{"providedExports":true}},"./node_modules/core-js/library/modules/_to-absolute-index.js":{"id":"./node_modules/core-js/library/modules/_to-absolute-index.js","buildMeta":{"providedExports":true}},"./node_modules/core-js/library/modules/_shared-key.js":{"id":"./node_modules/core-js/library/modules/_shared-key.js","buildMeta":{"providedExports":true}},"./node_modules/core-js/library/modules/_shared.js":{"id":"./node_modules/core-js/library/modules/_shared.js","buildMeta":{"providedExports":true}},"./node_modules/core-js/library/modules/_library.js":{"id":"./node_modules/core-js/library/modules/_library.js","buildMeta":{"providedExports":true}},"./node_modules/core-js/library/modules/_uid.js":{"id":"./node_modules/core-js/library/modules/_uid.js","buildMeta":{"providedExports":true}},"./node_modules/core-js/library/modules/_enum-bug-keys.js":{"id":"./node_modules/core-js/library/modules/_enum-bug-keys.js","buildMeta":{"providedExports":true}},"./node_modules/core-js/library/modules/_object-gops.js":{"id":"./node_modules/core-js/library/modules/_object-gops.js","buildMeta":{"providedExports":true}},"./node_modules/core-js/library/modules/_object-pie.js":{"id":"./node_modules/core-js/library/modules/_object-pie.js","buildMeta":{"providedExports":true}},"./node_modules/core-js/library/modules/_to-object.js":{"id":"./node_modules/core-js/library/modules/_to-object.js","buildMeta":{"providedExports":true}},"./node_modules/babel-runtime/helpers/classCallCheck.js":{"id":"./node_modules/babel-runtime/helpers/classCallCheck.js","buildMeta":{"providedExports":true}},"./node_modules/babel-runtime/helpers/possibleConstructorReturn.js":{"id":"./node_modules/babel-runtime/helpers/possibleConstructorReturn.js","buildMeta":{"providedExports":true}},"./node_modules/babel-runtime/helpers/typeof.js":{"id":"./node_modules/babel-runtime/helpers/typeof.js","buildMeta":{"providedExports":true}},"./node_modules/babel-runtime/core-js/symbol/iterator.js":{"id":"./node_modules/babel-runtime/core-js/symbol/iterator.js","buildMeta":{"providedExports":true}},"./node_modules/core-js/library/fn/symbol/iterator.js":{"id":"./node_modules/core-js/library/fn/symbol/iterator.js","buildMeta":{"providedExports":true}},"./node_modules/core-js/library/modules/es6.string.iterator.js":{"id":"./node_modules/core-js/library/modules/es6.string.iterator.js","buildMeta":{"providedExports":true}},"./node_modules/core-js/library/modules/_string-at.js":{"id":"./node_modules/core-js/library/modules/_string-at.js","buildMeta":{"providedExports":true}},"./node_modules/core-js/library/modules/_iter-define.js":{"id":"./node_modules/core-js/library/modules/_iter-define.js","buildMeta":{"providedExports":true}},"./node_modules/core-js/library/modules/_redefine.js":{"id":"./node_modules/core-js/library/modules/_redefine.js","buildMeta":{"providedExports":true}},"./node_modules/core-js/library/modules/_iterators.js":{"id":"./node_modules/core-js/library/modules/_iterators.js","buildMeta":{"providedExports":true}},"./node_modules/core-js/library/modules/_iter-create.js":{"id":"./node_modules/core-js/library/modules/_iter-create.js","buildMeta":{"providedExports":true}},"./node_modules/core-js/library/modules/_object-create.js":{"id":"./node_modules/core-js/library/modules/_object-create.js","buildMeta":{"providedExports":true}},"./node_modules/core-js/library/modules/_object-dps.js":{"id":"./node_modules/core-js/library/modules/_object-dps.js","buildMeta":{"providedExports":true}},"./node_modules/core-js/library/modules/_html.js":{"id":"./node_modules/core-js/library/modules/_html.js","buildMeta":{"providedExports":true}},"./node_modules/core-js/library/modules/_set-to-string-tag.js":{"id":"./node_modules/core-js/library/modules/_set-to-string-tag.js","buildMeta":{"providedExports":true}},"./node_modules/core-js/library/modules/_wks.js":{"id":"./node_modules/core-js/library/modules/_wks.js","buildMeta":{"providedExports":true}},"./node_modules/core-js/library/modules/_object-gpo.js":{"id":"./node_modules/core-js/library/modules/_object-gpo.js","buildMeta":{"providedExports":true}},"./node_modules/core-js/library/modules/web.dom.iterable.js":{"id":"./node_modules/core-js/library/modules/web.dom.iterable.js","buildMeta":{"providedExports":true}},"./node_modules/core-js/library/modules/es6.array.iterator.js":{"id":"./node_modules/core-js/library/modules/es6.array.iterator.js","buildMeta":{"providedExports":true}},"./node_modules/bootstrap/dist/js/bootstrap.js":{"id":"./node_modules/bootstrap/dist/js/bootstrap.js","buildMeta":{"providedExports":true}},"./node_modules/core-js/library/modules/_iter-step.js":{"id":"./node_modules/core-js/library/modules/_iter-step.js","buildMeta":{"providedExports":true}},"./node_modules/core-js/library/modules/_wks-ext.js":{"id":"./node_modules/core-js/library/modules/_wks-ext.js","buildMeta":{"providedExports":true}},"./node_modules/babel-runtime/core-js/symbol.js":{"id":"./node_modules/babel-runtime/core-js/symbol.js","buildMeta":{"providedExports":true}},"./node_modules/core-js/library/fn/symbol/index.js":{"id":"./node_modules/core-js/library/fn/symbol/index.js","buildMeta":{"providedExports":true}},"./node_modules/core-js/library/modules/es6.symbol.js":{"id":"./node_modules/core-js/library/modules/es6.symbol.js","buildMeta":{"providedExports":true}},"./node_modules/core-js/library/modules/_meta.js":{"id":"./node_modules/core-js/library/modules/_meta.js","buildMeta":{"providedExports":true}},"./node_modules/core-js/library/modules/_wks-define.js":{"id":"./node_modules/core-js/library/modules/_wks-define.js","buildMeta":{"providedExports":true}},"./node_modules/core-js/library/modules/_enum-keys.js":{"id":"./node_modules/core-js/library/modules/_enum-keys.js","buildMeta":{"providedExports":true}},"./node_modules/core-js/library/modules/_is-array.js":{"id":"./node_modules/core-js/library/modules/_is-array.js","buildMeta":{"providedExports":true}},"./node_modules/core-js/library/modules/_object-gopn-ext.js":{"id":"./node_modules/core-js/library/modules/_object-gopn-ext.js","buildMeta":{"providedExports":true}},"./node_modules/core-js/library/modules/_object-gopn.js":{"id":"./node_modules/core-js/library/modules/_object-gopn.js","buildMeta":{"providedExports":true}},"./node_modules/core-js/library/modules/_object-gopd.js":{"id":"./node_modules/core-js/library/modules/_object-gopd.js","buildMeta":{"providedExports":true}},"./node_modules/core-js/library/modules/es6.object.to-string.js":{"id":"./node_modules/core-js/library/modules/es6.object.to-string.js","buildMeta":{"providedExports":true}},"./node_modules/core-js/library/modules/es7.symbol.async-iterator.js":{"id":"./node_modules/core-js/library/modules/es7.symbol.async-iterator.js","buildMeta":{"providedExports":true}},"./node_modules/core-js/library/modules/es7.symbol.observable.js":{"id":"./node_modules/core-js/library/modules/es7.symbol.observable.js","buildMeta":{"providedExports":true}},"./node_modules/babel-runtime/helpers/inherits.js":{"id":"./node_modules/babel-runtime/helpers/inherits.js","buildMeta":{"providedExports":true}},"./node_modules/babel-runtime/core-js/object/set-prototype-of.js":{"id":"./node_modules/babel-runtime/core-js/object/set-prototype-of.js","buildMeta":{"providedExports":true}},"./node_modules/core-js/library/fn/object/set-prototype-of.js":{"id":"./node_modules/core-js/library/fn/object/set-prototype-of.js","buildMeta":{"providedExports":true}},"./node_modules/core-js/library/modules/es6.object.set-prototype-of.js":{"id":"./node_modules/core-js/library/modules/es6.object.set-prototype-of.js","buildMeta":{"providedExports":true}},"./node_modules/core-js/library/modules/_set-proto.js":{"id":"./node_modules/core-js/library/modules/_set-proto.js","buildMeta":{"providedExports":true}},"./node_modules/babel-runtime/core-js/object/create.js":{"id":"./node_modules/babel-runtime/core-js/object/create.js","buildMeta":{"providedExports":true}},"./node_modules/core-js/library/fn/object/create.js":{"id":"./node_modules/core-js/library/fn/object/create.js","buildMeta":{"providedExports":true}},"./node_modules/core-js/library/modules/es6.object.create.js":{"id":"./node_modules/core-js/library/modules/es6.object.create.js","buildMeta":{"providedExports":true}},"./node_modules/react-popper/lib/esm/Manager.js":{"id":"./node_modules/react-popper/lib/esm/Manager.js","buildMeta":{"exportsType":"namespace","providedExports":["ManagerContext","default"]}},"./node_modules/create-react-context/lib/index.js":{"id":"./node_modules/create-react-context/lib/index.js","buildMeta":{"providedExports":true}},"./node_modules/create-react-context/lib/implementation.js":{"id":"./node_modules/create-react-context/lib/implementation.js","buildMeta":{"providedExports":true}},"./node_modules/prop-types/index.js":{"id":"./node_modules/prop-types/index.js","buildMeta":{"providedExports":true}},"./node_modules/prop-types/factoryWithTypeCheckers.js":{"id":"./node_modules/prop-types/factoryWithTypeCheckers.js","buildMeta":{"providedExports":true}},"./node_modules/gud/index.js":{"id":"./node_modules/gud/index.js","buildMeta":{"providedExports":true}},"./node_modules/react-popper/lib/esm/utils.js":{"id":"./node_modules/react-popper/lib/esm/utils.js","buildMeta":{"exportsType":"namespace","providedExports":["unwrapArray","safeInvoke"]}},"./node_modules/react-popper/lib/esm/Reference.js":{"id":"./node_modules/react-popper/lib/esm/Reference.js","buildMeta":{"exportsType":"namespace","providedExports":["default"]}},"./node_modules/react-router/es/index.js":{"id":"./node_modules/react-router/es/index.js","buildMeta":{"exportsType":"namespace","providedExports":["MemoryRouter","Prompt","Redirect","Route","Router","StaticRouter","Switch","generatePath","matchPath","withRouter"]}},"./node_modules/react-router/es/MemoryRouter.js":{"id":"./node_modules/react-router/es/MemoryRouter.js","buildMeta":{"exportsType":"namespace","providedExports":["default"]}},"./node_modules/react-router/node_modules/warning/warning.js":{"id":"./node_modules/react-router/node_modules/warning/warning.js","buildMeta":{"providedExports":true}},"./node_modules/react-router/es/Router.js":{"id":"./node_modules/react-router/es/Router.js","buildMeta":{"exportsType":"namespace","providedExports":["default"]}},"./node_modules/react-router/es/Prompt.js":{"id":"./node_modules/react-router/es/Prompt.js","buildMeta":{"exportsType":"namespace","providedExports":["default"]}},"./node_modules/react-router/es/Redirect.js":{"id":"./node_modules/react-router/es/Redirect.js","buildMeta":{"exportsType":"namespace","providedExports":["default"]}},"./node_modules/react-router/es/generatePath.js":{"id":"./node_modules/react-router/es/generatePath.js","buildMeta":{"exportsType":"namespace","providedExports":["default"]}},"./node_modules/path-to-regexp/index.js":{"id":"./node_modules/path-to-regexp/index.js","buildMeta":{"providedExports":true}},"./node_modules/path-to-regexp/node_modules/isarray/index.js":{"id":"./node_modules/path-to-regexp/node_modules/isarray/index.js","buildMeta":{"providedExports":true}},"./node_modules/react-router/es/Route.js":{"id":"./node_modules/react-router/es/Route.js","buildMeta":{"exportsType":"namespace","providedExports":["default"]}},"./node_modules/react-router/es/matchPath.js":{"id":"./node_modules/react-router/es/matchPath.js","buildMeta":{"exportsType":"namespace","providedExports":["default"]}},"./node_modules/react-router/es/StaticRouter.js":{"id":"./node_modules/react-router/es/StaticRouter.js","buildMeta":{"exportsType":"namespace","providedExports":["default"]}},"./node_modules/react-router/es/Switch.js":{"id":"./node_modules/react-router/es/Switch.js","buildMeta":{"exportsType":"namespace","providedExports":["default"]}},"./node_modules/react-router/es/withRouter.js":{"id":"./node_modules/react-router/es/withRouter.js","buildMeta":{"exportsType":"namespace","providedExports":["default"]}},"./node_modules/hoist-non-react-statics/dist/hoist-non-react-statics.cjs.js":{"id":"./node_modules/hoist-non-react-statics/dist/hoist-non-react-statics.cjs.js","buildMeta":{"providedExports":true}},"./node_modules/react-router-dom/es/index.js":{"id":"./node_modules/react-router-dom/es/index.js","buildMeta":{"exportsType":"namespace","providedExports":["BrowserRouter","HashRouter","Link","MemoryRouter","NavLink","Prompt","Redirect","Route","Router","StaticRouter","Switch","generatePath","matchPath","withRouter"]}},"./node_modules/react-router-dom/es/BrowserRouter.js":{"id":"./node_modules/react-router-dom/es/BrowserRouter.js","buildMeta":{"exportsType":"namespace","providedExports":["default"]}},"./node_modules/react-router-dom/node_modules/warning/warning.js":{"id":"./node_modules/react-router-dom/node_modules/warning/warning.js","buildMeta":{"providedExports":true}},"./node_modules/react-router-dom/es/Router.js":{"id":"./node_modules/react-router-dom/es/Router.js","buildMeta":{"exportsType":"namespace","providedExports":["default"]}},"./node_modules/react-router-dom/es/HashRouter.js":{"id":"./node_modules/react-router-dom/es/HashRouter.js","buildMeta":{"exportsType":"namespace","providedExports":["default"]}},"./node_modules/react-router-dom/es/Link.js":{"id":"./node_modules/react-router-dom/es/Link.js","buildMeta":{"exportsType":"namespace","providedExports":["default"]}},"./node_modules/react-router-dom/es/MemoryRouter.js":{"id":"./node_modules/react-router-dom/es/MemoryRouter.js","buildMeta":{"exportsType":"namespace","providedExports":["default"]}},"./node_modules/react-router-dom/es/NavLink.js":{"id":"./node_modules/react-router-dom/es/NavLink.js","buildMeta":{"exportsType":"namespace","providedExports":["default"]}},"./node_modules/react-router-dom/es/Route.js":{"id":"./node_modules/react-router-dom/es/Route.js","buildMeta":{"exportsType":"namespace","providedExports":["default"]}},"./node_modules/react-router-dom/es/Prompt.js":{"id":"./node_modules/react-router-dom/es/Prompt.js","buildMeta":{"exportsType":"namespace","providedExports":["default"]}},"./node_modules/react-router-dom/es/Redirect.js":{"id":"./node_modules/react-router-dom/es/Redirect.js","buildMeta":{"exportsType":"namespace","providedExports":["default"]}},"./node_modules/react-router-dom/es/StaticRouter.js":{"id":"./node_modules/react-router-dom/es/StaticRouter.js","buildMeta":{"exportsType":"namespace","providedExports":["default"]}},"./node_modules/react-router-dom/es/Switch.js":{"id":"./node_modules/react-router-dom/es/Switch.js","buildMeta":{"exportsType":"namespace","providedExports":["default"]}},"./node_modules/react-router-dom/es/generatePath.js":{"id":"./node_modules/react-router-dom/es/generatePath.js","buildMeta":{"exportsType":"namespace","providedExports":["default"]}},"./node_modules/react-router-dom/es/matchPath.js":{"id":"./node_modules/react-router-dom/es/matchPath.js","buildMeta":{"exportsType":"namespace","providedExports":["default"]}},"./node_modules/react-router-dom/es/withRouter.js":{"id":"./node_modules/react-router-dom/es/withRouter.js","buildMeta":{"exportsType":"namespace","providedExports":["default"]}},"./node_modules/react-transition-group/index.js":{"id":"./node_modules/react-transition-group/index.js","buildMeta":{"providedExports":true}},"./node_modules/react-transition-group/CSSTransition.js":{"id":"./node_modules/react-transition-group/CSSTransition.js","buildMeta":{"providedExports":true}},"./node_modules/dom-helpers/class/addClass.js":{"id":"./node_modules/dom-helpers/class/addClass.js","buildMeta":{"providedExports":true}},"./node_modules/dom-helpers/class/hasClass.js":{"id":"./node_modules/dom-helpers/class/hasClass.js","buildMeta":{"providedExports":true}},"./node_modules/dom-helpers/class/removeClass.js":{"id":"./node_modules/dom-helpers/class/removeClass.js","buildMeta":{"providedExports":true}},"./node_modules/react-transition-group/Transition.js":{"id":"./node_modules/react-transition-group/Transition.js","buildMeta":{"providedExports":true}},"./node_modules/react-lifecycles-compat/react-lifecycles-compat.es.js":{"id":"./node_modules/react-lifecycles-compat/react-lifecycles-compat.es.js","buildMeta":{"exportsType":"namespace","providedExports":["polyfill"]}},"./node_modules/react-transition-group/utils/PropTypes.js":{"id":"./node_modules/react-transition-group/utils/PropTypes.js","buildMeta":{"providedExports":true}},"./node_modules/react-transition-group/ReplaceTransition.js":{"id":"./node_modules/react-transition-group/ReplaceTransition.js","buildMeta":{"providedExports":true}},"./node_modules/react-transition-group/TransitionGroup.js":{"id":"./node_modules/react-transition-group/TransitionGroup.js","buildMeta":{"providedExports":true}},"./node_modules/react-transition-group/utils/ChildMapping.js":{"id":"./node_modules/react-transition-group/utils/ChildMapping.js","buildMeta":{"providedExports":true}},"./node_modules/reactstrap/dist/reactstrap.es.js":{"id":"./node_modules/reactstrap/dist/reactstrap.es.js","buildMeta":{"exportsType":"namespace","providedExports":["Alert","Container","Row","Col","Navbar","NavbarBrand","NavbarToggler","Nav","NavItem","NavDropdown","NavLink","Breadcrumb","BreadcrumbItem","Button","ButtonDropdown","ButtonGroup","ButtonToolbar","Dropdown","DropdownItem","DropdownMenu","DropdownToggle","Fade","Badge","Card","CardLink","CardGroup","CardDeck","CardColumns","CardBody","CardBlock","CardFooter","CardHeader","CardImg","CardImgOverlay","Carousel","UncontrolledCarousel","CarouselControl","CarouselItem","CarouselIndicators","CarouselCaption","CardSubtitle","CardText","CardTitle","Popover","PopoverContent","PopoverBody","PopoverTitle","PopoverHeader","Progress","Modal","ModalHeader","ModalBody","ModalFooter","PopperContent","PopperTargetHelper","Tooltip","Table","ListGroup","Form","FormFeedback","FormGroup","FormText","Input","InputGroup","InputGroupAddon","InputGroupButton","InputGroupButtonDropdown","InputGroupText","Label","CustomInput","Media","Pagination","PaginationItem","PaginationLink","TabContent","TabPane","Jumbotron","Collapse","ListGroupItem","ListGroupItemText","ListGroupItemHeading","UncontrolledAlert","UncontrolledButtonDropdown","UncontrolledCollapse","UncontrolledDropdown","UncontrolledNavDropdown","UncontrolledTooltip","Util"]}},"./node_modules/classnames/index.js":{"id":"./node_modules/classnames/index.js","buildMeta":{"providedExports":true}},"./node_modules/lodash.isfunction/index.js":{"id":"./node_modules/lodash.isfunction/index.js","buildMeta":{"providedExports":true}},"./node_modules/lodash.isobject/index.js":{"id":"./node_modules/lodash.isobject/index.js","buildMeta":{"providedExports":true}},"./node_modules/reactstrap/node_modules/react-popper/lib/react-popper.js":{"id":"./node_modules/reactstrap/node_modules/react-popper/lib/react-popper.js","buildMeta":{"exportsType":"namespace","providedExports":["Manager","Target","Popper","placements","Arrow"]}},"./node_modules/reactstrap/node_modules/react-popper/lib/Manager.js":{"id":"./node_modules/reactstrap/node_modules/react-popper/lib/Manager.js","buildMeta":{"exportsType":"namespace","providedExports":["default"]}},"./node_modules/reactstrap/node_modules/react-popper/lib/Target.js":{"id":"./node_modules/reactstrap/node_modules/react-popper/lib/Target.js","buildMeta":{"exportsType":"namespace","providedExports":["default"]}},"./node_modules/reactstrap/node_modules/react-popper/lib/Popper.js":{"id":"./node_modules/reactstrap/node_modules/react-popper/lib/Popper.js","buildMeta":{"exportsType":"namespace","providedExports":["placements","default"]}},"./node_modules/reactstrap/node_modules/react-popper/lib/Arrow.js":{"id":"./node_modules/reactstrap/node_modules/react-popper/lib/Arrow.js","buildMeta":{"exportsType":"namespace","providedExports":["default"]}},"./node_modules/lodash.tonumber/index.js":{"id":"./node_modules/lodash.tonumber/index.js","buildMeta":{"providedExports":true}},"./node_modules/recompose/dist/Recompose.esm.js":{"id":"./node_modules/recompose/dist/Recompose.esm.js","buildMeta":{"exportsType":"namespace","providedExports":["mapProps","withProps","withPropsOnChange","withHandlers","defaultProps","renameProp","renameProps","flattenProp","withState","withStateHandlers","withReducer","branch","renderComponent","renderNothing","shouldUpdate","pure","onlyUpdateForKeys","onlyUpdateForPropTypes","withContext","getContext","lifecycle","toClass","toRenderProps","fromRenderProps","setStatic","setPropTypes","setDisplayName","compose","getDisplayName","wrapDisplayName","shallowEqual","isClassComponent","createSink","componentFromProp","nest","hoistStatics","componentFromStream","componentFromStreamWithConfig","mapPropsStream","mapPropsStreamWithConfig","createEventHandler","createEventHandlerWithConfig","setObservableConfig"]}},"./node_modules/@babel/runtime/helpers/esm/extends.js":{"id":"./node_modules/@babel/runtime/helpers/esm/extends.js","buildMeta":{"exportsType":"namespace","providedExports":["default"]}},"./node_modules/@babel/runtime/helpers/esm/inheritsLoose.js":{"id":"./node_modules/@babel/runtime/helpers/esm/inheritsLoose.js","buildMeta":{"exportsType":"namespace","providedExports":["default"]}},"./node_modules/@babel/runtime/helpers/esm/objectWithoutPropertiesLoose.js":{"id":"./node_modules/@babel/runtime/helpers/esm/objectWithoutPropertiesLoose.js","buildMeta":{"exportsType":"namespace","providedExports":["default"]}},"./node_modules/change-emitter/lib/index.js":{"id":"./node_modules/change-emitter/lib/index.js","buildMeta":{"providedExports":true}},"./node_modules/symbol-observable/es/index.js":{"id":"./node_modules/symbol-observable/es/index.js","buildMeta":{"exportsType":"namespace","providedExports":["default"]}},"./node_modules/webpack/buildin/harmony-module.js":{"id":"./node_modules/webpack/buildin/harmony-module.js","buildMeta":{"providedExports":true}},"./node_modules/symbol-observable/es/ponyfill.js":{"id":"./node_modules/symbol-observable/es/ponyfill.js","buildMeta":{"exportsType":"namespace","providedExports":["default"]}},"./node_modules/source-map-support/source-map-support.js":{"id":"./node_modules/source-map-support/source-map-support.js","buildMeta":{"providedExports":true}},"./node_modules/source-map-support/node_modules/source-map/source-map.js":{"id":"./node_modules/source-map-support/node_modules/source-map/source-map.js","buildMeta":{"providedExports":true}},"./node_modules/source-map-support/node_modules/source-map/lib/source-map-generator.js":{"id":"./node_modules/source-map-support/node_modules/source-map/lib/source-map-generator.js","buildMeta":{"providedExports":true}},"./node_modules/source-map-support/node_modules/source-map/lib/base64-vlq.js":{"id":"./node_modules/source-map-support/node_modules/source-map/lib/base64-vlq.js","buildMeta":{"providedExports":true}},"./node_modules/source-map-support/node_modules/source-map/lib/base64.js":{"id":"./node_modules/source-map-support/node_modules/source-map/lib/base64.js","buildMeta":{"providedExports":true}},"./node_modules/source-map-support/node_modules/source-map/lib/util.js":{"id":"./node_modules/source-map-support/node_modules/source-map/lib/util.js","buildMeta":{"providedExports":true}},"./node_modules/source-map-support/node_modules/source-map/lib/array-set.js":{"id":"./node_modules/source-map-support/node_modules/source-map/lib/array-set.js","buildMeta":{"providedExports":true}},"./node_modules/source-map-support/node_modules/source-map/lib/mapping-list.js":{"id":"./node_modules/source-map-support/node_modules/source-map/lib/mapping-list.js","buildMeta":{"providedExports":true}},"./node_modules/source-map-support/node_modules/source-map/lib/source-map-consumer.js":{"id":"./node_modules/source-map-support/node_modules/source-map/lib/source-map-consumer.js","buildMeta":{"providedExports":true}},"./node_modules/source-map-support/node_modules/source-map/lib/binary-search.js":{"id":"./node_modules/source-map-support/node_modules/source-map/lib/binary-search.js","buildMeta":{"providedExports":true}},"./node_modules/source-map-support/node_modules/source-map/lib/quick-sort.js":{"id":"./node_modules/source-map-support/node_modules/source-map/lib/quick-sort.js","buildMeta":{"providedExports":true}},"./node_modules/source-map-support/node_modules/source-map/lib/source-node.js":{"id":"./node_modules/source-map-support/node_modules/source-map/lib/source-node.js","buildMeta":{"providedExports":true}},"path":{"id":"path","buildMeta":{"providedExports":true}},"fs":{"id":"fs","buildMeta":{"providedExports":true}},"./node_modules/buffer-from/index.js":{"id":"./node_modules/buffer-from/index.js","buildMeta":{"providedExports":true}},"module":{"id":"module","buildMeta":{"providedExports":true}},"./node_modules/styled-components/dist/styled-components.esm.js":{"id":"./node_modules/styled-components/dist/styled-components.esm.js","buildMeta":{"exportsType":"namespace","providedExports":["default","css","keyframes","injectGlobal","isStyledComponent","consolidateStreamedStyles","ThemeProvider","withTheme","ServerStyleSheet","StyleSheetManager","__DO_NOT_USE_OR_YOU_WILL_BE_HAUNTED_BY_SPOOKY_GHOSTS"]}},"./node_modules/stylis/stylis.js":{"id":"./node_modules/stylis/stylis.js","buildMeta":{"providedExports":true}},"./node_modules/stylis-rule-sheet/index.js":{"id":"./node_modules/stylis-rule-sheet/index.js","buildMeta":{"providedExports":true}},"stream":{"id":"stream","buildMeta":{"providedExports":true}},"./node_modules/react-is/index.js":{"id":"./node_modules/react-is/index.js","buildMeta":{"providedExports":true}},"./node_modules/react-is/cjs/react-is.development.js":{"id":"./node_modules/react-is/cjs/react-is.development.js","buildMeta":{"providedExports":true}}}}